photonai_conformal/__init__.py
photonai_conformal/mapie_wrapper.py
photonai_conformal/photonai_conformal.json
photonai_conformal/version.py
photonai_conformal-0.0.6.dist-info/AUTHORS
photonai_conformal-0.0.6.dist-info/LICENSE
photonai_conformal-0.0.6.dist-info/METADATA
photonai_conformal-0.0.6.dist-info/WHEEL
photonai_conformal-0.0.6.dist-info/pbr.json
photonai_conformal-0.0.6.dist-info/top_level.txt
photonai_conformal-0.0.6.dist-info/RECORD
