Metadata-Version: 2.1
Name: photonai-conformal
Version: 0.0.6
Home-page: https://github.com//photonai_conformal/
Download-URL: https://pypi.org/project/photonai_conformal/#files
Author: Jan Ernsting
Author-email: j.ernsting@uni-muenster.de
Project-URL: Source Code, https://github.com/wwu-mmll/photonai_conformal/
Project-URL: Documentation, https://wwu-mmll.github.io/photonai_conformal/
Project-URL: Bug Tracker, https://github.com/wwu-mmll/photonai_conformal/issues
Keywords: machine learning,deep learning
License-File: LICENSE
License-File: AUTHORS
Requires-Dist: photonai
Requires-Dist: pbr
Requires-Dist: mapie
